taolu/__init__.py
taolu/demo/__init__.py
taolu/demo/demo_base.py
taolu/demo/demo_facenet.py
taolu/demo/demo_resnet18.py
taolu/demo/demo_resnet50.py
taolu/demo/demo_vgg16.py
taolu/demo/demo_yolo_former.py
taolu/demo/demo_yolov1.py
taolu/demo/play.py
taolu/demo/yolo_temp.py
taolu/demo/demo_images/__init__.py
taolu/nlp/__init__.py
taolu/vision/__init__.py
taolu/vision/application/__init__.py
taolu/vision/application/face/__init__.py
taolu/vision/application/face/facenet.py
taolu/vision/base_nets/__init__.py
taolu/vision/base_nets/base_net.py
taolu/vision/base_nets/facenet.json
taolu/vision/base_nets/resnet18.json
taolu/vision/base_nets/resnet50.json
taolu/vision/base_nets/vgg16.json
taolu/vision/base_nets/vgg16.py
taolu/vision/base_nets/yolov1.json
taolu/vision/base_nets/__pycache__/__init__.cpython-36.pyc
taolu/vision/base_nets/__pycache__/base_net.cpython-36.pyc
taolu/vision/gen/__init__.py
taolu/vision/jobs/__init__.py
taolu/vision/jobs/classification.py
taolu/vision/jobs/face_recognition.py
taolu/vision/jobs/object_detection.py
taolu/vision/utils/__init__.py
taolu/vision/utils/cal101_util.py
taolu/vision/utils/cifar_util.py
taolu/vision/utils/trainers/__init__.py
taolu/vision/utils/trainers/triplet_trainer.py
taolu/vision/utils/transformers/__init__.py
taolu/vision/utils/transformers/cross_entropy_transformer.py
taolu/vision/utils/transformers/empty_transformer.py
taolu/vision/utils/transformers/facenet_transformer.py
taolu/vision/utils/transformers/mse_transformer.py
taolu/vision/utils/transformers/transformer.py
taolu/vision/utils/transformers/yolo_transformer.py
taolu/vision/vision_units/__init__.py
taolu/vision/vision_units/base_unit.py
taolu/vision/vision_units/inception_block.py
taolu/vision/vision_units/l2_norm.py
taolu/vision/vision_units/linear.py
taolu/vision/vision_units/res_block.py
taolu/vision/vision_units/losses/__init__.py
taolu/vision/vision_units/losses/cross_entropy_loss.py
taolunet-0.1.5.dist-info/METADATA
taolunet-0.1.5.dist-info/RECORD
taolunet-0.1.5.dist-info/WHEEL
taolunet-0.1.5.dist-info/top_level.txt
