Metadata-Version: 2.1
Name: taolunet
Version: 0.1.5
Summary: Taolunet on Pytorch.
Home-page: https://github.com/ainrichman/taolunet
Author: Wei ZUO
Author-email: victorzuo@outlook.com
License: LICENSE.txt
Platform: UNKNOWN
Requires-Dist: torch (>=0.4.0)
Requires-Dist: numpy (>=1.14.5)
Requires-Dist: torchvision (>=0.2.1)
Requires-Dist: opencv-python (>=3.3.0.10)
Requires-Dist: scipy (>=1.0.0)
